jwcnotipy/__init__.py
jwcnotipy/blocks.py
jwcnotipy/notifiers.py
jwcnotipy/requirements.txt
jwcnotipy-0.0.4.dist-info/METADATA
jwcnotipy-0.0.4.dist-info/WHEEL
jwcnotipy-0.0.4.dist-info/RECORD
