Metadata-Version: 2.1
Name: jwcnotipy
Version: 0.0.4
Summary: Provides a decorator that passes notifications to Slack
Project-URL: Homepage, https://github.com/abercon/noddy_notifier
Project-URL: Bug Tracker, https://github.com/abercon/noddy_notifier/issues
Author-email: Joshua W-Christy <me@joshuawchristy.com>
Classifier: Operating System :: OS Independent
Classifier: Programming Language :: Python :: 3
Requires-Python: >=3.7
